dnsdb_mock_apiserver
