Metadata-Version: 1.1
Name: dnsdb-mock-apiserver
Version: 0.1.0a1
Summary: DnsDB Mock API Server
Home-page: http://team.dnsdb.io
Author: DnsDB Team
Author-email: team@dnsdb.io
License: BSD License
Platform: UNKNOWN
Classifier: Development Status :: 3 - Alpha
Classifier: Environment :: Console
Classifier: License :: OSI Approved :: BSD License
Classifier: Natural Language :: Chinese (Simplified)
Classifier: Operating System :: OS Independent
Classifier: Programming Language :: Python
Classifier: Programming Language :: Python :: 2.7
Classifier: Programming Language :: Python :: 3.3
Classifier: Programming Language :: Python :: 3.4
Classifier: Programming Language :: Python :: 3.5
